mdoc/__init__.py
mdoc/mdoc.py
mdoc-0.0.9.dist-info/METADATA
mdoc-0.0.9.dist-info/RECORD
mdoc-0.0.9.dist-info/WHEEL
mdoc-0.0.9.dist-info/entry_points.txt
mdoc-0.0.9.dist-info/top_level.txt
