Metadata-Version: 2.1
Name: mdoc
Version: 0.0.9
Summary: Modular documents
Home-page: https://github.com/eshapiro42/mdoc
Author: Eric Shapiro
Author-email: eshapiro42@gmail.com
License: UNKNOWN
Platform: UNKNOWN
Classifier: Programming Language :: Python
Classifier: License :: OSI Approved :: Apache Software License
Classifier: Operating System :: OS Independent
Requires-Dist: pathlib
